talkback_messenger/__init__.py
talkback_messenger/__main__.py
talkback_messenger/clients/talkback_client.py
talkback_messenger/exceptions.py
talkback_messenger/models/config.py
talkback_messenger/models/resource.py
talkback_messenger/models/subscription.py
talkback_messenger/models/utils.py
talkback_messenger/slack_builder.py
talkback_messenger/talkback_bot_core.py
talkback_messenger/utils.py
talkback_messenger-0.10.0.dist-info/LICENSE
talkback_messenger-0.10.0.dist-info/METADATA
talkback_messenger-0.10.0.dist-info/WHEEL
talkback_messenger-0.10.0.dist-info/entry_points.txt
talkback_messenger-0.10.0.dist-info/RECORD
