Metadata-Version: 2.3
Name: talkback-messenger
Version: 0.10.0
Summary: Finds the InfoSec content you're interested in from talkback.sh, and posts it to Slack in a digestible format.
License: GPL-3.0
Keywords: infosec,security,slack,OSINT,talkback
Author: PaperMtn
Author-email: papermtn@protonmail.com
Requires-Python: >=3.12,<4.0
Classifier: Intended Audience :: Information Technology
Classifier: License :: OSI Approved :: GNU General Public License v3 (GPLv3)
Classifier: Programming Language :: Python :: 3
Classifier: Programming Language :: Python :: 3.12
Classifier: Programming Language :: Python :: 3.13
Requires-Dist: aiohttp (>=3.11.11,<4.0.0)
Requires-Dist: beautifulsoup4 (>=4.12.3,<5.0.0)
Requires-Dist: gql (>=3.5.1,<4.0.0)
Requires-Dist: loguru (>=0.7.3,<0.8.0)
Requires-Dist: pyyaml (>=6.0.2,<7.0.0)
Requires-Dist: requests (>=2.32.3,<3.0.0)
Requires-Dist: slack-sdk (>=3.34.0,<4.0.0)
Project-URL: Blog, https://papermtn.co.uk/category/tools/talkback-messenger/
Project-URL: Homepage, https://github.com/PaperMtn/talkback-messenger
Project-URL: Repository, https://github.com/PaperMtn/talkback-messenger
